git_monitor/__init__.py
git_monitor/libs/__init__.py
git_monitor/libs/monitor.py
git_monitor-0.1.6.dist-info/LICENSE
git_monitor-0.1.6.dist-info/METADATA
git_monitor-0.1.6.dist-info/WHEEL
git_monitor-0.1.6.dist-info/RECORD
