Metadata-Version: 2.1
Name: git-monitor
Version: 0.1.6
Summary: Automatic print the git status of the package your are developing.
Home-page: https://github.com/baliuzeger/py_git_monitor
Keywords: git,log,datascience
Author: bali
Author-email: baliuzeger@gmail.com
Requires-Python: >=3.11,<4.0
Classifier: Programming Language :: Python :: 3
Classifier: Programming Language :: Python :: 3.11
Classifier: Programming Language :: Python :: 3.12
Requires-Dist: GitPython
Requires-Dist: python-dotenv
Project-URL: Repository, https://github.com/baliuzeger/py_git_monitor
